{"id":"tt0100405","cast":[{"character":"Vivian Ward","name":"Julia Roberts"},{"character":"Edward Lewis","name":"Richard Gere"},{"character":"James Morse","name":"Ralph Bellamy"},{"character":"Philip Stuckey","name":"Jason Alexander"},{"character":"Barney Thompson","name":"Héctor Elizondo"},{"character":"Mr. Hollister","name":"Larry Miller"},{"character":"Kit De Luca","name":"Laura San Giacomo"},{"character":"David Morse","name":"Alex Hyde-White"},{"character":"Bridget","name":"Elinor Donahue"},{"character":"Elizabeth Stuckey","name":"Amy Yasbeck"},{"character":"Susan","name":"Judith Baldwin"},{"character":"Detective","name":"Hank Azaria"},{"character":"Mark","name":"John David Carson"},{"character":"Maitre D'","name":"Michael French"},{"character":"Waiter","name":"Allan Kent"},{"character":"Senator Adams","name":"Stacy Keach, Sr."},{"character":"Skateboard Kid","name":"Scott Marshall"}],"crew":[{"job":"Director","name":"Garry Marshall"},{"job":"Producer","name":"Arnon Milchan"},{"job":"Producer","name":"Steven Reuther"},{"job":"Original Music Composer","name":"James Newton Howard"}],"title":"Pretty Woman","genres":["Romance","Comedy"],"keywords":["prostitute","capitalism","cinderella","expensive restaurant","sports car","workaholic","fire escape","friendship","los angeles","piano"],"original_language":"en","rating":"R","release_date":"1990-03-23","revenue":463000000.0,"runtime":119,"summary":"Because of his extreme wealth and suave good looks, Edward Lewis could seemingly have any woman he wants, that committed significant other which he needs on his arm at social events to further how he makes his money as a corporate raider. However, he focuses more on his corporate raiding pursuits with his partner in crime, Philip Stuckey, his lawyer of ten years, than those women, with every significant other he's had in his life feeling neglected and eventually leaving him, this fact about which he is just coming to the realization. In Beverly Hills, Edward, in needing that woman on his arms as he and Philip work toward taking over the company owned by the increasingly insolvent James Morse, decides, based on a chance encounter, to hire Hollywood Boulevard hooker Vivian Ward as his escort for the week 24/7. He does so because he wants to have a professional who would be committed to the work, yet not have any commitments to her after the week is over. Beyond their chance encounter, ...","tokens":["a","success","wealthi","lawyer","edward","lewi","hire","beauti","unlik","prostitut","vivian","ward","julia","robert","sunset","blvd","bring","along","variou","busi","event","an","attract","develop","two","edward","find","harder","harder","let","infecti","kind","heart","vivian","go","businessman","edward","lewi","richard","gere","break","girlfriend","want","beck","call","swanki","parti","held","partner","philip","stuckei","cut","loos","stuckei","lotu","he","get","lost","stop","along","hollywood","boulevard","direct","hooker","vivenn","ward","julia","robert","she","charg","get","end","drive","hotel","beverlei","hill","he","ask","penthous","suit","whim","pai","stai","night","although","seem","uncomfort","first","the","follow","morn","ask","stai","week","$3000","he","also","give","monei","cloth","sai","need","beck","call","string","attach","she","call","room","mate","kit","laura","san","giacomo","leav","monei","rent","goe","shop","rodeo","drive","appropri","cloth","howev","snooti","saleswomen","serv","still","dress","like","hooker","return","hotel","get","stop","hotel","manag","barnei","hector","elizondo","he","want","make","clear","make","except","hotel","edward","special","guest","vivienn","get","upset","still","outfit","dinner","barnei","help","along","coach","dinner","etiquett","when","edward","return","amaz","vivienn","new","look","the","busi","dinner","goe","well","edward","preoccupi","deal","afterward","the","next","dai","vivienn","tell","experi","shoppingt","previou","dai","edward","take","back","spend","obscen","amount","monei","cloth","leav","go","back","work","transform","hooker","ladi","she","goe","back","shop","previou","dai","show","big","mistak","made","back","hotel","look","like","genuin","guest","edward","get","home","still","busi","work","take","bath","togeth","talk","night","past","end","todai","the","follow","dai","edward","take","vivienn","polo","while","vivienn","chat","david","mors","grandson","man","involv","edward","latest","deal","philip","worri","spy","edward","reassur","tell","met","philip","come","vivienn","when","return","hotel","furiou","edward","tell","plan","leav","persuad","see","week","edward","leav","work","earli","next","dai","take","vivienn","date","opera","privat","jet","she","clearli","move","music","sai","if","i","forget","tell","later","i","wonder","time","tonight","on","return","hotel","fall","asleep","first","time","seen","get","readi","bed","kiss","lip","client","make","love","partner","rather","client","hooker","over","breakfast","edward","offer","put","apart","continu","see","feel","insult","sai","fairytal","want","he","goe","work","without","resolv","situat","kit","come","hotel","see","fallen","deni","edward","meet","mors","close","deal","chang","mind","last","minut","hi","time","vivienn","shown","anoth","wai","take","time","enjoi","life","work","he","want","creat","thing","rather","make","monei","philip","livid","goe","hotel","vivienn","blame","chang","edward","come","onto","hit","edward","return","pull","chuck","vivienn","leav","seen","back","home","kit","pack","leav","san","franscisco","edward","get","car","chauffeur","took","home","rather","go","airport","goe","apart","climb","fire","escpa","despit","afraid","height","rose","mouth","woo","like","fairi","stori"],"tmdb_score_value":7.1,"tmdb_score_count":2423,"imdb_score_value":7.0,"imdb_score_count":241690,"meta_score_value":51.0,"meta_score_count":241690}