{"id":"tt0947798","cast":[{"character":"Nina Sayers","name":"Natalie Portman"},{"character":"Lily","name":"Mila Kunis"},{"character":"Thomas Leroy","name":"Vincent Cassel"},{"character":"Erica Sayers","name":"Barbara Hershey"},{"character":"Beth MacIntyre","name":"Winona Ryder"},{"character":"David Moreau","name":"Benjamin Millepied"},{"character":"Veronica","name":"Ksenia Solo"},{"character":"Galina","name":"Kristina Anapau"},{"character":"Madeline","name":"Janet Montgomery"},{"character":"Andrew","name":"Sebastian Stan"},{"character":"Tom","name":"Toby Hemingway"},{"character":"Sergio","name":"Sergio Torrado"},{"character":"Mr. Fithian","name":"Mark Margolis"},{"character":"Mrs. Fithian","name":"Tina Sloan"},{"character":"Mr. Stein","name":"Abraham Aronofsky"},{"character":"Mrs. Stein","name":"Charlotte Aronofsky"},{"character":"Georgina","name":"Marcia Jean Kurtz"},{"character":"Sebastian","name":"Shaun O'Hagan"},{"character":"Scott","name":"Chris Gartin"},{"character":"Susie","name":"Deborah Offner"}],"crew":[{"job":"Director","name":"Darren Aronofsky"},{"job":"Screenplay","name":"Mark Heyman"},{"job":"Screenplay","name":"Andres Heinz"},{"job":"Original Music Composer","name":"Clint Mansell"},{"job":"Screenplay","name":"John J. McLaughlin"},{"job":"Producer","name":"Scott Franklin"},{"job":"Producer","name":"Jerry Fruchtman"},{"job":"Producer","name":"Rose Garnett"},{"job":"Producer","name":"Mike Medavoy"},{"job":"Producer","name":"Arnold Messer"},{"job":"Producer","name":"Joseph P. Reidy"},{"job":"Producer","name":"Brian Oliver"}],"title":"Black Swan","genres":["Drama","Thriller"],"keywords":["dancing","competition","sex","dancer","obsession","paranoia","insanity","suspense","ballet","new york city","heartbreak","mental illness","madness","swan lake","ballerina","body horror"],"original_language":"en","rating":"R","release_date":"2010-12-02","revenue":327803740.0,"runtime":108,"summary":"Nina (Portman) is a ballerina in a New York City ballet company whose life, like all those in her profession, is completely consumed with dance. She lives with her obsessive former ballerina mother Erica (Hershey) who exerts a suffocating control over her. When artistic director Thomas Leroy (Cassel) decides to replace prima ballerina Beth MacIntyre (Ryder) for the opening production of their new season, Swan Lake, Nina is his first choice. But Nina has competition: a new dancer, Lily (Kunis), who impresses Leroy as well. Swan Lake requires a dancer who can play both the White Swan with innocence and grace, and the Black Swan, who represents guile and sensuality. Nina fits the White Swan role perfectly but Lily is the personification of the Black Swan. As the two young dancers expand their rivalry into a twisted friendship, Nina begins to get more in touch with her dark side - a recklessness that threatens to destroy her.","tokens":["the","movi","open","nina","sayer","natali","portman","young","ballerina","mid","twenti","danc","prologu","swan","lake","swan","lake","ballet","princess","turn","white","swan","turn","back","man","swear","etern","fidel","in","ballet","betrai","black","swan","evil","magician","daughter","magician","transform","look","exactli","like","princess","order","trick","princ","fallen","love","in","end","princess","commit","suicid","princ","infidel","doom","remain","swan","forev","as","nina","danc","role","princess","magician","appear","place","curs","princess","nina","wake","apart","danc","sequenc","dream","she","begin","daili","ballet","stretch","tell","mother","dream","mother","unintention","ignor","nina","mention","director","thoma","leroi","pronounc","tomah","name","french","ballet","compani","promis","featur","season","mother","agre","long","enough","nina","goe","ballet","studio","learn","beth","winona","ryder","lead","princip","dancer","put","pastur","due","ag","40","as","result","thoma","vincent","cassel","look","new","face","lead","thoma","announc","compani","first","perform","season","rework","swan","lake","he","casual","walk","among","dancer","practis","nonchalantli","tap","sever","girl","shoulder","talk","he","tell","tap","attend","regular","rehears","tap","meet","later","princip","studio","nina","see","beth","emot","meltdown","privat","dress","room","throw","thing","break","full","length","mirror","after","beth","leav","nina","decid","take","peek","insid","she","sit","beth","chair","stare","mirror","surround","globe","light","she","begin","go","beth","thing","stash","sever","item","pocket","specif","perfum","diamond","ear","nail","file","tube","lipstick","she","sneak","beth","dress","room","later","princip","studio","audit","held","find","beth","replac","swan","princess","nina","danc","white","swan","impecc","thoma","tell","nina","danc","black","swan","as","nina","begin","danc","audit","interrupt","late","arriv","new","dancer","lili","mila","kuni","alreadi","fear","imperfect","disappoint","thoma","lose","focu","lili","noisili","close","door","stop","despit","flawless","perform","white","swan","thoma","impress","nina","perform","state","fail","captur","sensual","black","swan","nina","goe","home","mother","burst","tear","practic","danc","move","crack","big","toe","nail","later","mother","tuck","nina","tell","go","thoma","next","dai","tell","finish","black","swan","danc","mother","tell","need","lie","nina","nod","defeat","agreement","the","next","dai","nina","visit","thoma","offic","tell","finish","black","swan","danc","home","want","role","he","tell","decid","give","anoth","dancer","veronica","ksenia","soto","she","sai","okai","begin","leav","slam","door","ask","give","he","grab","face","kiss","passion","anger","unwant","advanc","nina","bite","lip","run","offic","shock","impress","thoma","the","girl","begin","run","hall","find","chosen","new","swan","queen","feel","certain","get","role","nina","congratul","veronica","get","the","girl","run","see","post","walk","back","nina","berat","cruel","joke","walk","hall","stun","confus","nina","goe","look","post","as","approach","sever","girl","gather","around","shout","congratul","overjoi","nauseou","run","bathroom","call","mother","on","stall","tell","part","when","leav","stall","see","word","whore","written","mirror","red","lipstick","frantic","struggl","wipe","when","nina","get","home","mother","order","beauti","pink","white","frost","cake","strawberri","cream","favorit","local","bakeri","present","nina","walk","door","celebr","nina","acquir","role","ballet","her","mother","start","cut","slice","nina","refus","tell","eat","someth","like","mother","give","look","nina","continu","sai","stomach","still","knot","becom","angri","mother","begin","throw","cake","leav","nina","feel","guilti","she","accept","slice","take","small","bite","over","next","sever","dai","stress","role","inabl","perform","get","nina","she","begin","see","darker","version","random","passer","thoma","hold","gala","offici","announc","beth","retir","nina","rise","swan","queen","nina","goe","bathroom","wai","encount","lili","come","in","front","nina","lili","take","panti","put","purs","sit","vaniti","she","congratul","nina","role","nina","uncomfort","attempt","excus","lili","playfulli","ask","stai","nina","leav","as","nina","thoma","leav","parti","thoma","briefli","call","back","insid","intox","ey","drip","black","mascara","cry","beth","confront","nina","ask","suck","thoma","cock","get","role","nina","offend","tell","beth","everyon","beth","continu","rant","thoma","appear","diffus","situat","sooth","beth","call","my","littl","princess","beth","shout","thoma","lead","nina","he","take","nina","back","place","when","sit","couch","brusqu","ask","virgin","she","look","awai","smile","uncomfort","he","ask","like","make","love","answer","give","homework","assign","must","touch","find","sexual","mai","better","inhabit","role","later","nina","mother","help","dress","bed","see","scratch","nina","back","ask","nina","sai","noth","rash","mother","becom","angri","hint","nina","scratch","like","sinc","younger","thought","nina","nina","tri","brush","mother","grab","hand","take","bathroom","cut","fingernail","scissor","she","accident","cut","nina","finger","apolog","profus","continu","trim","nina","nail","nina","wake","next","morn","begin","touch","thoma","ask","when","becom","arous","goe","faster","turn","as","get","closer","turn","head","left","startl","realiz","mother","asleep","chair","next","bed","the","next","dai","compani","practis","girl","run","cry","hyster","she","run","teacher","comfort","ask","happen","she","sai","beth","hospit","accid","got","hit","pass","car","later","nina","sit","edg","fountain","thoma","tell","believ","beth","threw","oncom","traffic","she","visit","beth","hospit","find","room","fill","beauti","flower","card","wish","quick","recoveri","as","beth","lai","comatos","bed","nina","lift","sheet","drape","beth","see","metal","bar","stick","leg","huge","infect","gash","calf","horrifi","quickli","turn","leav","bump","beth","nurs","lesli","lyle","ask","she","goe","practic","still","cannot","get","passion","black","swan","perform","suddenli","light","go","thoma","call","someon","turn","back","still","peopl","rehears","the","light","come","back","clearli","disappoint","thoma","send","dancer","home","step","danc","nina","partner","as","danc","togeth","slowli","move","hand","thigh","begin","touch","after","deep","kiss","let","go","walk","awai","call","shoulder","seduc","seduc","danc","nina","call","plead","turn","back","nina","feel","defeat","attempt","perfect","sit","alon","cri","studio","lili","arriv","see","nina","cry","light","cigarett","walk","lili","chat","casual","impli","thoma","tendenc","sleep","troup","nina","tri","defend","lili","realiz","nina","crush","thoma","joke","infuri","thought","nina","get","upset","leav","the","next","dai","thoma","angrili","ask","nina","need","time","comment","lili","take","easi","he","sai","busi","whine","fervent","defend","sai","anger","nina","track","lili","troup","dress","room","greet","banter","dancer","sai","queen","grace","presenc","turf","lili","tell","shut","get","talk","nina","nina","berat","lili","tell","thoma","cry","lili","look","abash","sai","try","help","nina","tell","need","help","lili","walk","awai","irrit","that","night","nina","mother","work","nina","toe","shoe","erica","nina","mother","make","small","talk","sound","condescend","nina","start","answer","slight","hostil","without","look","erica","her","mother","ask","nina","scratch","nina","unintention","paus","long","enough","erica","believ","nina","sai","erica","tell","take","shirt","nina","refus","erica","stand","nina","demand","nina","sai","bite","tone","befor","erica","get","confirm","knock","door","she","answer","door","talk","quickli","someon","close","nina","ask","erica","sai","on","nina","demand","know","erica","still","tell","run","door","open","she","see","lili","wait","elev","nina","walk","hallwai","ask","lili","knew","live","lili","respond","sarcasm","but","nina","look","angri","lili","laughingli","sai","ask","thoma","secretari","erica","open","door","sai","nina","need","come","rest","nina","tell","shut","door","erica","slam","lili","invit","nina","sai","erica","open","door","tell","tell","nina","come","back","insid","also","ask","lili","leav","nina","push","door","open","grab","stuff","leav","lili","despit","mother","protest","shout","hall","night","long","dai","work","stai","home","nina","lili","go","local","bar","drink","food","nina","uptight","lili","offer","pill","relax","sai","would","last","hour","nina","turn","she","goe","bathroom","return","see","lili","slip","content","pill","drink","flirt","two","gui","call","tom","tobi","hemingwai","jerri","though","tell","real","name","andrew","nina","reassur","lili","pill","last","hour","down","glass","the","two","crazi","drug","night","club","two","gui","when","nina","next","lucid","find","hook","man","bathroom","she","quickli","leav","find","cab","lili","run","catch","thei","take","taxi","back","nina","apart","lili","come","onto","nina","begin","gentli","rub","nina","crotch","nina","stop","hold","lili","hand","when","get","back","apart","nina","mother","wait","ask","nina","late","nina","drunk","somewhat","belliger","final","sai","i","two","gui","name","tom","jerri","i","fuck","laugh","nina","mother","horrifi","slap","across","face","nina","grab","lili","run","room","barricad","door","wood","cleat","yell","mother","leav","alon","she","turn","around","look","lili","walk","start","passion","kiss","thei","move","bed","lili","nina","undress","underwear","lili","rip","nina","panti","lili","begin","oral","pleasur","nina","briefli","see","lili","morph","back","lili","scare","lili","stop","two","continu","sex","lili","perform","cunnilingu","nina","eventu","climax","lili","sai","sweet","girl","morph","back","dark","nina","rais","pillow","smother","nina","wake","next","morn","hangov","like","headach","find","lili","gone","realiz","late","rehears","as","mother","sit","quietli","live","room","nina","yell","ask","wake","erica","sai","role","destroi","nina","rush","door","tell","erica","move","when","nina","arriv","ballet","studio","find","lili","costum","practic","routin","rest","troup","when","lili","walk","nina","sai","fill","thoma","ask","nina","question","lili","left","hous","night","lili","claim","went","home","place","tom","spent","night","last","time","saw","nina","club","when","nina","bring","happen","bedroom","lili","flatter","nina","lesbian","wet","dream","she","playfulli","ask","nina","good","nina","get","embarrass","leav","look","uncomfort","frustrat","wonder","lovemak","lili","realli","happen","a","littl","later","nina","fit","swan","costum","when","done","lili","walk","sai","thoma","made","lili","nina","altern","enrag","afraid","nina","find","thoma","beg","make","lili","altern","convinc","lili","try","steal","role","as","nina","begin","cry","thoma","sooth","tell","paranoid","he","tell","person","try","sabotag","nina","nina","that","night","nina","practis","piano","player","suddenli","stop","plai","get","leav","tell","nina","life","he","tell","practic","long","leav","alon","studio","as","begin","danc","light","shut","shed","practis","thoma","she","call","someon","turn","light","back","see","cloak","figur","dart","around","shadow","sorcer","dream","she","hear","laughter","follow","nois","find","thoma","sex","lili","morph","nina","work","tabl","behind","curtain","lili","smile","thoma","laugh","thi","bring","tear","nina","ey","run","back","dress","room","grab","item","took","beth","room","still","in","fit","hysteria","nina","goe","hospit","find","beth","sit","motionless","wheelchair","mere","shadow","woman","us","nina","quietli","place","note","item","stole","tabl","next","beth","beth","suddenli","stir","grab","nina","arm","beth","angri","ask","nina","look","see","item","tabl","she","ask","nina","amus","irrit","voic","stole","nina","sai","want","perfect","like","beth","as","beth","look","item","sai","noth","notic","nail","file","she","continu","sai","noth","suddenli","stab","face","file","repeatedli","nina","final","grab","nail","file","beth","hand","run","fearfulli","room","elev","as","get","elev","drop","bloodi","nail","file","nina","return","home","dash","hyster","kitchen","wash","hand","cover","beth","blood","when","turn","kitchen","light","hear","someon","whisper","sweet","girl","turn","light","back","see","beth","stand","face","cover","blood","she","run","bathroom","vomit","toilet","she","call","hall","mother","walk","toward","mother","art","studio","hear","voic","come","studio","as","peer","imagin","mother","paint","move","talk","she","run","start","tear","everyth","imagin","beth","come","toward","bloodi","face","mother","walk","astonish","ask","nina","nina","run","past","mother","bedroom","erica","close","behind","as","tri","reach","nina","nina","slam","door","hand","break","nina","barricad","insid","pipe","as","nina","stand","skin","begin","shift","take","bird","like","textur","ey","start","turn","red","knee","joint","violent","invert","shape","bird","the","hallucin","disori","nina","fall","hit","head","bed","post","knock","nina","wake","next","dai","normal","dai","sock","rubber","band","hand","headach","she","look","mother","sit","next","bed","bandag","hand","nina","ask","mother","hand","cover","erica","sai","prevent","scratch","night","nina","suddenli","realiz","must","late","sai","need","get","ballet","compani","open","dai","her","mother","sai","call","let","know","nina","feel","well","abl","perform","night","nina","furiou","get","bed","she","goe","door","mother","lock","door","remov","door","knob","nina","turn","around","yell","mother","let","erica","tell","well","role","taken","nina","grab","mother","broken","hand","pull","chair","as","mother","cri","hold","injur","hand","nina","take","door","knob","cushion","walk","toward","door","her","mother","reach","ask","happen","sweet","girl","nina","sai","harsh","evil","tone","gone","walk","room","nina","arriv","ballet","ignor","whisper","troup","pass","camera","follow","behind","she","find","lili","costum","talk","thoma","hall","prepar","take","stage","lead","nina","confid","tell","thoma","readi","perform","goe","sit","dress","room","lili","ask","go","behind","thoma","follow","room","sai","alreadi","told","lili","perform","nina","sai","take","stage","compani","mar","controversi","beth","incid","thoma","look","slightli","amus","impress","audac","tell","get","readi","nina","goe","timid","rigid","perform","rehears","while","wing","see","lili","flirt","on","male","dancer","also","becom","distract","lili","danc","stage","subsequ","lift","lose","concentr","caus","lead","male","drop","she","recov","interv","thoma","enrag","ask","hell","nina","blame","danc","partner","thoma","walk","awai","when","enter","dress","room","lili","sit","dress","tabl","put","make","nina","yell","get","room","lili","taunt","nina","sai","perhap","danc","black","swan","danc","nina","fit","danc","begin","fight","lili","morph","nina","nina","struggl","nina","push","lili","full","length","mirror","beth","destroi","shatter","as","fight","escal","nina","grab","piec","mirror","stab","lili","stomach","unsur","nina","hide","bleed","bodi","bathroom","put","black","swan","make","she","take","stage","begin","danc","passion","abandon","as","danc","everyth","thoma","ask","begin","physic","transform","larg","black","swan","stage","grow","feather","wing","she","danc","part","better","ever","crowd","give","stand","ovat","piec","end","nina","run","stage","toward","thoma","front","everyon","kiss","passion","final","seduc","movement","he","smile","tell","go","back","second","bow","after","leav","stage","nina","goe","dress","room","chang","next","act","realiz","blood","start","pour","bathroom","door","nina","place","towel","grow","pool","blood","hear","knock","door","when","open","door","lili","stand","she","apolog","thing","turn","congratul","nina","amaz","perform","black","swan","nina","shock","bewild","lili","smile","walk","awai","nina","turn","around","remov","towel","find","blood","she","turn","look","broken","mirror","piec","smash","mirror","still","floor","suddenli","move","hand","abdomen","she","bleed","reach","wound","pull","broken","shard","glass","in","unhing","delusion","mind","nina","stab","black","swan","danc","imagin","lili","despit","wound","dress","final","act","white","swan","nina","danc","second","act","beautifulli","entranc","audienc","see","small","stain","blood","grow","mid","section","white","costum","in","final","scene","last","act","white","swan","goe","top","larg","structur","commit","suicid","nina","grace","look","suitor","turn","fall","slow","motion","onto","mattress","mother","sit","audienc","smile","cry","when","curtain","fall","thoma","overjoi","newli","infatu","nina","he","smile","ador","kneel","congratul","crowd","ballerina","gather","around","star","nina","speak","instead","smile","listen","prais","lili","suddenli","gasp","first","notic","immens","blood","stain","form","nina","costum","someon","call","help","thoma","frantic","ask","what","nina","calmli","quietli","utter","i","perfect","the","crowd","continu","roar","applaus","screen","slowli","fade","white"],"tmdb_score_value":7.4,"tmdb_score_count":6006,"imdb_score_value":8.0,"imdb_score_count":611815,"meta_score_value":79.0,"meta_score_count":611815}