{"id":"tt0112851","cast":[{"character":"El Mariachi","name":"Antonio Banderas"},{"character":"Carolina","name":"Salma Hayek"},{"character":"Bucho","name":"Joaquim de Almeida"},{"character":"Short Bartender","name":"Cheech Marin"},{"character":"Buscemi","name":"Steve Buscemi"},{"character":"Right Hand","name":"Carlos Andrés Gómez"},{"character":"Pick-Up Guy","name":"Quentin Tarantino"},{"character":"Tavo","name":"Tito Larriva"},{"character":"Zamira","name":"Angel Aviles"},{"character":"Navajas","name":"Danny Trejo"},{"character":"Niño","name":"Abraham Verduzco"},{"character":"Campa","name":"Carlos Gallardo"},{"character":"Quino","name":"Albert Michel Jr."},{"character":"Buddy","name":"David Alvarado"},{"character":"Tourist Girl","name":"Angela Lanza"},{"character":"Mariachi Fan","name":"Elizabeth Rodriguez"}],"crew":[{"job":"Director","name":"Robert Rodriguez"},{"job":"Screenplay","name":"Robert Rodriguez"},{"job":"Producer","name":"Robert Rodriguez"},{"job":"Producer","name":"Bill Borden"}],"title":"Desperado","genres":["Thriller","Action","Crime"],"keywords":["gunslinger","anti terror","ambush","mexico","showdown","guitar","hitman","bartender","latinx lead","revenge","tragic hero","shootout","mariachi","explosion","extreme violence","brutality","drug lord","leg brace","concealed weapon","bookstore"],"original_language":"en","rating":"R","release_date":"1995-08-25","revenue":25405444.0,"runtime":104,"summary":"With this sequel to his prize-winning independent previous film, \"El Mariachi,\" director Robert Rodriquez joins the ranks of Sam Peckinpah and John Woo as a master of slick, glamorized ultra-violence. We pick up the story as a continuation of \"El Mariachi,\" where an itinerant musician, looking for work, gets mistaken for a hitman and thereby entangled in a web of love, corruption, and death. This time, he is out to avenge the murder of his lover and the maiming of his fretting hand, which occurred at the end of the earlier movie. However, the plot is recapitulated, and again, a case of mistaken identity leads to a very high body count, involvement with a beautiful woman who works for the local drug lord, and finally, the inevitable face-to-face confrontation and bloody showdown.","tokens":["an","unnam","man","steve","buscemi","walk","bar","the","custom","initi","hostil","toward","seem","notic","he","begin","tell","bar","anoth","town","clean","man","black","look","man","name","bucho","thi","stori","openli","frighten","men","well","bartend","cheech","marin","side","kick","tavo","tito","larriva","attempt","get","descript","man","face","buscemi","claim","know","remark","believ","man","head","wai","el","mariachi","antonio","bandera","man","stori","wake","dream","domino","love","interest","first","film","he","hear","knock","door","let","buscemi","it","reveal","buscemi","help","el","find","bucho","he","tell","el","find","bucho","bar","visit","buscemi","ask","el","reveng","el","simpli","state","buscemi","sai","glad","el","remark","buscemi","never","stomach","sort","thing","he","repli","neither","el","clean","appear","mariachi","walk","town","he","meet","young","boi","carri","guitar","teach","loosen","finger","plai","howev","wound","left","hand","moco","first","film","prevent","us","finger","left","hand","instead","teach","boi","pick","string","right","hand","meanwhil","bucho","appar","worri","man","black","come","he","order","men","keep","ey","stranger","bui","bulletproof","limo","el","goe","town","bar","the","patron","suspici","due","buscemi","stori","even","though","appear","noth","like","describ","the","biggest","mexican","i","ever","seen","life","except","black","cloth","thei","hold","gunpoint","open","guitar","search","weapon","told","guitar","case","see","guitar","thei","let","go","guitar","reveal","cover","insid","case","conceal","gun","thei","prepar","kill","eject","two","hidden","ruger","p90","45","acp","semi","automat","pistol","sleev","engag","bloodi","gunfight","men","meanwhil","hidden","room","sever","men","see","gunfight","video","monitor","tavo","execut","drug","pick","up","gui","quentin","tarantino","believ","betrai","el","proce","kill","men","except","bartend","tri","question","want","bartend","take","bucho","the","bartend","accident","shot","forehead","man","hidden","room","thei","attempt","shoot","run","bullet","try","us","fallen","men","gun","find","empti","final","man","find","on","tri","shoot","el","el","snap","neck","el","mariachi","leav","bar","unawar","follow","bartend","friend","associ","bucho","tavo","carri","two","semi","automat","pistol","44","calib","desert","eagl","ruger","p90","as","walk","notic","beauti","woman","salma","hayek","walk","toward","her","shock","express","man","behind","warn","el","shove","wai","time","shot","arm","manag","kill","tavo","later","el","awaken","bookstor","see","woman","stitch","arm","she","sai","name","carolina","he","want","go","hospit","sai","saw","he","ask","sai","bookstor","busi","good","he","fall","asleep","painkil","give","carolina","run","errand","come","back","bookstor","curiou","guitar","case","open","see","guitar","open","show","gun","she","grab","el","she","sai","know","you","gui","alwai","hear","stori","she","seem","afraid","he","offer","give","on","gun","gift","declin","he","leav","go","church","meet","buscemi","tell","get","still","el","follow","begin","argu","buscemi","unawar","follow","time","anoth","man","black","navaja","danni","trejo","stalk","el","throughout","film","he","tell","buscemi","mayb","quit","buscemi","approv","kill","navaja","throw","knive","el","also","hit","wound","take","cover","allei","navaja","wait","confid","entranc","bucho","limo","full","arm","men","bucho","girlfriend","pull","behind","attempt","question","he","kill","sever","knive","shot","dead","el","manag","escap","without","seen","run","littl","boi","earlier","want","show","el","real","guitar","el","follow","visibl","pain","bleed","profus","a","car","drive","man","insid","trade","guitar","boi","thei","drive","around","corner","see","el","the","man","car","attempt","pull","gun","el","faster","demand","guitar","thei","give","drive","awai","he","break","open","see","packet","cocain","he","question","littl","boi","sai","everyon","els","town","involv","busi","front","includ","carolina","bookstor","furiou","el","head","back","bookstor","meanwhil","bucho","men","return","navaja","dead","bodi","gate","compound","he","call","superior","ask","descript","man","sent","look","el","the","descript","match","navaja","bucho","let","men","kill","man","sent","he","chastis","second","command","believ","el","noth","legend","el","return","bookstor","yell","carolina","anger","fact","appar","work","man","try","kill","friend","dead","she","state","work","bucho","stuff","drop","pick","bookstor","paid","50","000","dollar","year","she","sai","us","littl","keep","bookstor","run","save","rest","case","ever","leav","join","allow","get","el","calm","lai","counter","fix","wound","promptli","shove","behind","counter","bucho","walk","he","question","seen","strang","peopl","state","call","el","behind","counter","attempt","load","gun","silent","unabl","time","bucho","leav","he","attempt","leav","follow","bucho","carolina","tell","would","suicid","wait","till","later","later","el","recov","wound","carolina","give","guitar","present","thei","attempt","plai","togeth","unabl","carolina","kiss","el","proce","sex","bedroom","meanwhil","bucho","call","men","town","tell","search","bookstor","el","kill","carolina","burn","bookstor","the","next","dai","el","awaken","carolina","sing","ey","close","see","silouhett","arm","men","curtain","he","proce","silent","pull","on","pistol","saw","doubl","barrel","shotgun","trip","carolina","wai","fire","kill","two","men","thei","attempt","escap","bookstor","see","fire","thei","make","wai","roof","gun","sever","men","find","wai","block","men","ground","carolina","jump","el","fire","men","throw","guitar","case","across","next","build","men","come","behind","forc","jump","backward","roof","fire","crook","he","land","roll","unharm","he","us","grenad","kill","last","gangster","while","hide","roof","el","see","bucho","drive","he","proce","aim","scope","wildei","magnum","pistol","bucho","head","hesit","see","bucho","face","put","gun","awai","carolina","ask","shoot","el","answer","take","refug","hotel","el","tell","escap","us","monei","stash","start","new","life","without","el","kill","bucho","carolina","sai","monei","hidden","book","burn","el","decid","call","friend","campa","quino","thei","show","shortli","follow","desert","part","town","bucho","men","find","campa","quino","reveal","special","case","campa","two","case","machin","gun","quino","case","rocket","launcher","thei","proce","kill","mani","bucho","men","along","carolina","help","howev","quino","kill","gangster","roof","campa","kill","run","ammo","the","littl","boi","also","caught","crossfir","badli","wound","el","carolina","kill","last","man","bucho","second","command","run","rush","boi","hospit","with","doctor","unsur","boi","live","el","angrili","head","bucho","ranch","settl","conflict","thei","arriv","find","surround","bucho","call","men","it","reveal","el","manito","bucho","cesar","brother","el","kill","bucho","earlier","bucho","howev","angri","carolina","betray","tell","el","put","hand","kill","carolina","even","el","kill","men","el","unabl","bear","anoth","love","death","eject","pistol","sleev","earlier","bar","shoot","bucho","dead","el","carolina","later","seen","hospit","get","know","boi","surviv","get","better","note","el","mariachi","carolina","got","awai","walk","awai","bucho","surviv","henchmen","reveal","el","tell","carolina","thank","leav","then","walk","desert","carolina","drive","jeep","ask","join","el","throw","awai","guitar","case","carolina","drive","stop","go","back","guitar","case","case","drive","awai","sunset"],"tmdb_score_value":6.8,"tmdb_score_count":1112,"imdb_score_value":7.2,"imdb_score_count":151754,"meta_score_value":55.0,"meta_score_count":151754}