{"id":"tt1690953","cast":[{"character":"Gru (voice)","name":"Steve Carell"},{"character":"Lucy (voice)","name":"Kristen Wiig"},{"character":"Eduardo/ El Macho (voice)","name":"Benjamin Bratt"},{"character":"Margo (voice)","name":"Miranda Cosgrove"},{"character":"Edith (voice)","name":"Dana Gaier"},{"character":"Agnes (voice)","name":"Elsie Fisher"},{"character":"Dr. Nefario (voice)","name":"Russell Brand"},{"character":"Floyd (voice)","name":"Ken Jeong"},{"character":"Silas (voice)","name":"Steve Coogan"},{"character":"Antonio (voice)","name":"Moisés Arias"},{"character":"Jillian (voice)","name":"Nasim Pedrad"},{"character":"Shannon (voice)","name":"Kristen Schaal"},{"character":"Kevin the Minion / Bob the Minion / Stuart the Minion / Additional Minions / Evil Minions (voice)","name":"Pierre Coffin"},{"character":"Additional Minions / Evil Minions / Italian Waiter (voice)","name":"Chris Renaud"},{"character":"Flight Attendant (voice)","name":"Vanessa Bayer"},{"character":"Additional Voices (voice)","name":"Ava Acres"},{"character":"Additional Voices (voice)","name":"Lori Alan"},{"character":"Additional Voices (voice)","name":"Jack Angel"},{"character":"Additional Voices (voice)","name":"Eva Bella"},{"character":"Additional Voices (voice)","name":"John Cygan"}],"crew":[{"job":"Director","name":"Pierre Coffin"},{"job":"Director","name":"Chris Renaud"},{"job":"Screenplay","name":"Cinco Paul"},{"job":"Producer","name":"Christopher Meledandri"},{"job":"Screenplay","name":"Ken Daurio"},{"job":"Original Music Composer","name":"Heitor Pereira"},{"job":"Producer","name":"Janet Healy"}],"title":"Despicable Me 2","genres":["Animation","Comedy","Family"],"keywords":["parent child relationship","secret agent","bakery","good vs evil","falling in love","family","duringcreditsstinger","first date","minions"],"original_language":"en","rating":"PG","release_date":"2013-06-25","revenue":970761860.0,"runtime":98,"summary":"While Gru, the ex-supervillain is adjusting to family life and an attempted honest living in the jam business, a secret Arctic laboratory is stolen. The Anti-Villain League decides it needs an insider's help and recruits Gru in the investigation. Together with the eccentric AVL agent, Lucy Wilde, Gru concludes that his prime suspect is the presumed dead supervillain, El Macho, whose his teenage son is also making the moves on his eldest daughter, Margo. Seemingly blinded by his overprotectiveness of his children and his growing mutual attraction to Lucy, Gru seems on the wrong track even as his minions are being quietly kidnapped en masse for some malevolent purpose.","tokens":["a","secret","laboratori","near","arctic","circl","stolen","mysteri","vehicl","us","giant","magnet","the","anti","villain","leagu","avl","recruit","former","super","villain","gru","devot","father","margo","edith","agn","find","evil","person","stole","lab","contain","power","mutagen","known","px","41","make","indestruct","extrem","aggress","monster","live","organ","gru","ex","villain","know","villain","work","refus","gru","learn","dr","nefario","friend","assist","decid","leav","new","employ","miss","evil","gru","reluctantli","partner","undercov","avl","agent","luci","wild","togeth","search","the","paradis","shop","mall","given","bakeri","call","bake","my","dai","headquart","gru","suspect","mexican","restaur","owner","eduardo","perez","super","villain","call","el","macho","bad","gui","becam","gru","inspir","villain","supposedli","di","skysurf","tnt","laden","shark","center","activ","volcano","gru","luci","break","eduardo","restaur","night","find","jar","secret","recip","salsa","noth","prove","eduardo","culprit","meanwhil","agn","express","wish","mother","somedai","suspect","gru","fall","love","luci","gru","tell","relationship","luci","strictli","profession","gru","luci","investig","wig","merchant","floyd","eagl","san","gru","still","suspici","eduardo","after","investig","gru","set","horribl","dinner","date","woman","name","shannon","notic","gru","wig","threaten","humili","luckili","luci","bump","rescu","date","shoot","shannon","tranquil","dart","thei","take","shannon","home","sai","good","night","gru","realiz","agn","right","romant","feel","luci","the","next","dai","avl","arrest","floyd","eagl","san","claim","frame","almost","empti","mutagen","jar","found","shop","the","investig","close","luci","reassign","australia","befor","leav","luci","give","gru","lipstick","taser","remind","thi","leav","gru","heartbroken","love","cannot","find","courag","ask","date","instead","bring","girl","eduardo","cinco","de","mayo","parti","find","proof","mexican","restauranteur","fact","super","villain","el","macho","gru","discov","helper","dr","nefario","captur","mutat","larg","number","gru","minion","us","px","41","turn","insan","savag","purpl","fur","monster","el","macho","plan","send","rocket","full","mutat","minion","major","citi","achiev","world","domin","el","macho","emphas","gru","could","team","would","becom","evil","follow","rule","citi","gru","avoid","answer","leav","daughter","margo","meantim","broken","eduardo","two","time","son","antonio","left","margo","anoth","girl","for","break","margo","heart","gru","us","freez","rai","freez","antonio","block","ic","on","flight","australia","luci","realiz","feel","gru","jump","plane","hang","glide","parti","she","captur","el","macho","know","avl","agent","pollito","pet","chicken","retriev","avl","id","badg","purs","fortun","dr","nefario","let","gru","know","happen","in","order","rescu","luci","gru","visit","el","macho","along","two","minion","cover","purpl","cupcak","frost","pretend","captur","two","mutant","creatur","fight","alongsid","daughter","dr","nefario","gru","team","sprai","mutat","minion","aw","tast","jelli","contain","power","antidot","dr","nefario","made","whereupon","revert","friendli","yellow","state","el","macho","take","mutagen","gru","dr","nefario","easili","overcom","us","fart","gun","luci","lipstick","taser","luci","howev","alreadi","strap","tnt","load","shark","rocket","gru","start","unti","rocket","launch","remot","button","press","el","macho","pet","chicken","pollito","the","rocket","fli","toward","lava","spew","volcano","el","macho","previous","fake","death","luci","accept","gru","invit","date","pair","dive","safeti","ocean","second","rocket","enter","volcano","on","hundr","forti","seven","date","later","gru","luci","marri","margo","edith","agn","final","mother","the","minion","close","rendit","i","swear","sung","miniones","underwear","y","m","c","a","whole","famili","danc","then","purpl","furri","minion","show","surpris","famili"],"tmdb_score_value":7.0,"tmdb_score_count":5619,"imdb_score_value":7.4,"imdb_score_count":323610,"meta_score_value":62.0,"meta_score_count":323610}